tmp_python_sample_yn1205/__init__.py
tmp_python_sample_yn1205/main.py
tmp_python_sample_yn1205-0.26.3.dist-info/METADATA
tmp_python_sample_yn1205-0.26.3.dist-info/WHEEL
tmp_python_sample_yn1205-0.26.3.dist-info/top_level.txt
tmp_python_sample_yn1205-0.26.3.dist-info/RECORD
