Metadata-Version: 2.1
Name: tmp-python-sample-yn1205
Version: 0.26.3
Summary: Sample tmp_python_sample_yn1205
Author-email: foo <bar@gmail.com>
Project-URL: Homepage, https://github.com/yana1205-test/tmp-python-sample-yn1205
Project-URL: Issues, https://github.com/yana1205-test/tmp-python-sample-yn1205/issues
Classifier: Development Status :: 3 - Alpha
Classifier: Intended Audience :: Developers
Classifier: Programming Language :: Python :: 3
Classifier: Programming Language :: Python :: 3.10
Classifier: License :: OSI Approved :: Apache Software License
Classifier: Operating System :: OS Independent
Requires-Python: >=3.10
Requires-Dist: jq ==1.6.0
Provides-Extra: dev
Requires-Dist: build >=1.0.3 ; extra == 'dev'
Requires-Dist: pep8-naming ; extra == 'dev'
Requires-Dist: toml-cli ; extra == 'dev'
Requires-Dist: types-PyYAML ; extra == 'dev'
Requires-Dist: types-setuptools ; extra == 'dev'
Requires-Dist: black ; extra == 'dev'
Requires-Dist: isort ; extra == 'dev'
Requires-Dist: pylint ; extra == 'dev'
Requires-Dist: pyclean ; extra == 'dev'
Requires-Dist: pytest ; extra == 'dev'
